<case><number>196</number><age>81</age><sex>M</sex><composition></composition><echogenicity></echogenicity><margins></margins><calcifications></calcifications><tirads></tirads><reportbacaf></reportbacaf><reporteco></reporteco><mark><image>1</image><svg>[{"points": [{"x": 466, "y": 144}, {"x": 469, "y": 139}, {"x": 468, "y": 131}, {"x": 463, "y": 120}, {"x": 460, "y": 117}, {"x": 450, "y": 114}, {"x": 439, "y": 112}, {"x": 433, "y": 106}, {"x": 427, "y": 103}, {"x": 419, "y": 102}, {"x": 406, "y": 102}, {"x": 389, "y": 105}, {"x": 360, "y": 110}, {"x": 350, "y": 115}, {"x": 345, "y": 121}, {"x": 339, "y": 129}, {"x": 338, "y": 137}, {"x": 340, "y": 144}, {"x": 343, "y": 152}, {"x": 348, "y": 158}, {"x": 352, "y": 162}, {"x": 359, "y": 165}, {"x": 385, "y": 173}, {"x": 393, "y": 179}, {"x": 403, "y": 183}, {"x": 410, "y": 188}, {"x": 441, "y": 194}, {"x": 456, "y": 193}, {"x": 460, "y": 192}, {"x": 465, "y": 186}, {"x": 467, "y": 184}, {"x": 470, "y": 179}, {"x": 469, "y": 166}, {"x": 469, "y": 160}, {"x": 468, "y": 156}, {"x": 471, "y": 144}], "annotation": {}, "regionType": "freehand"}, {"points": [{"x": 208, "y": 125}, {"x": 204, "y": 115}, {"x": 193, "y": 112}, {"x": 182, "y": 105}, {"x": 175, "y": 99}, {"x": 167, "y": 94}, {"x": 158, "y": 88}, {"x": 145, "y": 87}, {"x": 135, "y": 87}, {"x": 125, "y": 92}, {"x": 115, "y": 100}, {"x": 109, "y": 104}, {"x": 106, "y": 108}, {"x": 105, "y": 112}, {"x": 103, "y": 118}, {"x": 103, "y": 123}, {"x": 103, "y": 123}, {"x": 110, "y": 136}, {"x": 112, "y": 140}, {"x": 113, "y": 149}, {"x": 144, "y": 163}, {"x": 159, "y": 171}, {"x": 165, "y": 173}, {"x": 174, "y": 175}, {"x": 192, "y": 177}, {"x": 197, "y": 171}, {"x": 216, "y": 149}, {"x": 216, "y": 145}, {"x": 213, "y": 134}, {"x": 212, "y": 132}, {"x": 210, "y": 127}, {"x": 208, "y": 124}], "annotation": {}, "regionType": "freehand"}]</svg></mark></case>